setup.py
restclient/__init__.py
restclient.egg-info/PKG-INFO
restclient.egg-info/SOURCES.txt
restclient.egg-info/dependency_links.txt
restclient.egg-info/not-zip-safe
restclient.egg-info/requires.txt
restclient.egg-info/top_level.txt
restclient/test/__init__.py
restclient/test/test_everything.py