Metadata-Version: 1.0
Name: restclient
Version: 0.10.2
Summary: convenient library for writing REST clients
Home-page: http://github.com/thraxil/restclient/
Author: Anders Pearson
Author-email: anders@columbia.edu
License: BSD
Platform: any
